<gift ts="0.00" user="温柔一刀" giftname="小心心" giftcount="1"></gift>
<d p="0.01,1,24,7154951369349139237,1665895074106,0,3531237609440990,0" user="琳晴钰">交朋友交朋友交朋友交朋友交朋友交朋友交朋友交朋友交朋友交朋友</d>
<gift ts="0.01" user="网" giftname="小心心" giftcount="5"></gift>
<gift ts="0.10" user="空姐走秀" giftname="小心心" giftcount="11"></gift>
<d p="0.12,1,24,7154951369349139237,1665895074220,0,60669484323,0" user="梦女孩">什么歌</d>
<d p="0.16,1,24,7154951369349139237,1665895074261,0,1975148180668907,0" user="巍巍岁月">娜娜搞艺术有才华，比昊瀚还厉害！</d>
<d p="0.19,1,24,7154951369349139237,1665895074284,0,73164585940,0" user="西奈_川川子">小牛厉害</d>
<d p="0.23,1,24,7154951369349139237,1665895074328,0,3179413683836797,0" user="用户8058745584467">上人</d>
<d p="0.34,1,24,7154951369349139237,1665895074440,0,3681585956917981,0" user="奇闻异事">最爱昊艺 昊艺最帅</d>
<d p="0.35,1,24,7154951369349139237,1665895074449,0,68190653566,0" user="小清絮">都厉害</d>
<d p="0.57,1,24,7154951369349139237,1665895074668,0,101148728031,0" user="嘟嘟宝贝">他    他去不土木系不就快去看阿鲁</d>
<gift ts="0.73" user="空姐走秀" giftname="小心心" giftcount="12"></gift>
<d p="0.77,1,24,7154951369349139237,1665895074872,0,108131197116,0" user="依然">娜娜咪呢？娜娜咪呢？娜娜咪呢？娜娜咪呢？娜娜咪呢？娜娜咪呢？娜娜咪呢？娜娜咪呢？娜娜咪呢？娜娜咪呢？</d>
<d p="1.13,1,24,7154951369349139237,1665895075231,0,94124413933,0" user="越过">你老公当然很帅</d>
<gift ts="1.33" user="逍遥0528" giftname="小心心" giftcount="1"></gift>
<gift ts="1.34" user="温柔一刀" giftname="小心心" giftcount="1"></gift>
<d p="2.13,1,24,7154951369349139237,1665895076227,0,102301320449,0" user="纳尼！">给榜一点点关注</d>
<d p="2.14,1,24,7154951369349139237,1665895076235,0,98160055144,0" user="箱包">帅帅帅帅帅帅帅帅帅帅</d>
<d p="2.42,1,24,7154951369349139237,1665895076518,0,2853953637202775,0" user="峰回路转">点了，都点了[比心]</d>
<d p="2.43,1,24,7154951369349139237,1665895076527,0,72705238957,0" user="杜青。">[赞][赞][赞][赞][赞][赞][赞]</d>
<d p="2.44,1,24,7154951369349139237,1665895076538,0,2915542654518445,0" user="七仙女-">[赞][赞][赞][赞][赞][赞][赞][赞][赞][赞][赞][赞][赞][赞][赞][赞][赞][赞][赞][赞][赞][赞][赞][赞][赞][赞][赞][赞][赞][赞][赞][赞][赞][赞][赞][赞][赞][赞][赞][赞][赞][赞][赞][赞][赞][赞][赞][赞][赞][赞]</d>
<gift ts="2.84" user="熊有兵" giftname="人气票" giftcount="1"></gift>
<gift ts="2.85" user="莲子" giftname="小心心" giftcount="1"></gift>
<gift ts="3.00" user="有故事，也有酒" giftname="小心心" giftcount="1"></gift>
<gift ts="3.02" user="空姐走秀" giftname="小心心" giftcount="13"></gift>
<d p="3.04,1,24,7154951369349139237,1665895077142,0,102093894586,0" user="庞小妹">点关注哦！别把娜娜弄丢了</d>
<d p="3.20,1,24,7154951369349139237,1665895077299,0,69987923152429,0" user="如歌岁月">小牛</d>
<d p="3.63,1,24,7154951369349139237,1665895077731,0,95905012705,0" user="二爷">高级货</d>
<gift ts="4.20" user="逍遥0528" giftname="小心心" giftcount="1"></gift>
<d p="4.80,1,24,7154951369349139237,1665895078899,0,96966916250,0" user="用户1708229597470">帅帅昊艺[赞][赞]</d>
<gift ts="5.02" user="有故事，也有酒" giftname="小心心" giftcount="1"></gift>
<d p="5.41,1,24,7154951369349139237,1665895079507,0,3681585956917981,0" user="奇闻异事">最爱昊艺 昊艺最帅</d>
<gift ts="5.70" user="熊有兵" giftname="人气票" giftcount="1"></gift>
<gift ts="5.72" user="莲子" giftname="小心心" giftcount="1"></gift>
<gift ts="5.81" user="鱼的记忆@" giftname="小心心" giftcount="1"></gift>
<gift ts="6.01" user="空姐走秀" giftname="小心心" giftcount="13"></gift>
<gift ts="6.01" user="有故事，也有酒" giftname="小心心" giftcount="1"></gift>
<gift ts="6.02" user="空姐走秀" giftname="小心心" giftcount="1"></gift>
<d p="6.04,1,24,7154951369349139237,1665895080135,0,96060413747,0" user="神主">娜娜</d>
<d p="6.84,1,24,7154951369349139237,1665895080939,0,60065105469,0" user="十">点关注哦！别把娜娜弄丢了</d>
<gift ts="7.66" user="空姐走秀" giftname="小心心" giftcount="2"></gift>
<gift ts="7.84" user="富到平安" giftname="入团卡" giftcount="1"></gift>
<d p="8.59,1,24,7154951369349139237,1665895082692,0,3531237609440990,0" user="琳晴钰">交朋友交朋友交朋友交朋友交朋友交朋友交朋友交朋友交朋友交朋友</d>
<gift ts="8.96" user="鱼的记忆@" giftname="小心心" giftcount="1"></gift>
<gift ts="9.16" user="有故事，也有酒" giftname="小心心" giftcount="1"></gift>
<gift ts="9.17" user="空姐走秀" giftname="小心心" giftcount="3"></gift>
<gift ts="9.18" user="用户693210" giftname="小心心" giftcount="1"></gift>
<d p="10.36,1,24,7154951369349139237,1665895084458,0,92818990224,0" user="快乐">[雪花][无语][雪人]</d>
<gift ts="10.37" user="从零开始l7ig" giftname="玫瑰" giftcount="1"></gift>
<gift ts="10.57" user="富到平安" giftname="入团卡" giftcount="1"></gift>
<gift ts="10.78" user="空姐走秀" giftname="小心心" giftcount="4"></gift>
<d p="11.16,1,24,7154951369349139237,1665895085261,0,97680802750,0" user="丁玲">点关注哦！别把娜娜弄丢了</d>
<gift ts="11.17" user="从零开始l7ig" giftname="玫瑰" giftcount="2"></gift>
<d p="11.18,1,24,7154951369349139237,1665895085274,0,95545097969,0" user="可乐麻麻">艺艺帅</d>
<d p="11.38,1,24,7154951369349139237,1665895085475,0,729674955885271,0" user="细水长流">加油</d>
<d p="11.38,1,24,7154951369349139237,1665895085479,0,99248299809,0" user="Dan">昊艺帅</d>
<gift ts="11.64" user="有故事，也有酒" giftname="小心心" giftcount="1"></gift>
<d p="11.66,1,24,7154951369349139237,1665895085761,0,2598891493012379,0" user="向日葵">娜就艺起牛[赞][赞][赞][赞][赞][赞][赞][赞][赞][比心][比心][比心][比心][比心][比心][比心][比心][比心]</d>
<gift ts="12.17" user="空姐走秀" giftname="小心心" giftcount="5"></gift>
<gift ts="12.39" user="用户693210" giftname="小心心" giftcount="1"></gift>
<d p="12.40,1,24,7154951369349139237,1665895086502,0,96618626400,0" user="秋秋">今天个个状态满满</d>
<d p="12.62,1,24,7154951369349139237,1665895086718,0,106915901970,0" user="没有如果">艺艺像吴磊</d>
<d p="13.19,1,24,7154951369349139237,1665895087289,0,60065105469,0" user="十">心愿单</d>
<gift ts="13.39" user="空姐走秀" giftname="小心心" giftcount="6"></gift>
<d p="13.62,1,24,7154951369349139237,1665895087715,0,3681585956917981,0" user="奇闻异事">最爱昊艺 昊艺最帅</d>
<d p="13.64,1,24,7154951369349139237,1665895087739,0,1305853965112733,0" user="小生逍遥">牛很卖力.</d>
<d p="13.99,1,24,7154951369349139237,1665895088085,0,3531237609440990,0" user="琳晴钰">交朋友交朋友交朋友交朋友交朋友交朋友交朋友交朋友交朋友交朋友</d>
<gift ts="14.00" user="从零开始l7ig" giftname="玫瑰" giftcount="2"></gift>
<d p="14.00,1,24,7154951369349139237,1665895088103,0,99445271302,0" user="妮妮">点关注哦！别把娜娜弄丢了</d>
<d p="14.40,1,24,7154951369349139237,1665895088499,0,83569178172,0" user="富到平安">点关注哦！别把娜娜弄丢了</d>
<d p="14.80,1,24,7154951369349139237,1665895088902,0,93440099580,0" user="凤姐">艺艺帅</d>
<gift ts="14.81" user="有故事，也有酒" giftname="小心心" giftcount="1"></gift>
<d p="15.17,1,24,7154951369349139237,1665895089269,0,739302800633908,0" user="新疆全顺汽车租赁行">诚心诚意交朋友[感谢]新疆美景资源共享新疆美景诚心诚意交朋友诚心诚意交朋友新疆旅游自驾游咨询了解</d>
<d p="15.52,1,24,7154951369349139237,1665895089618,0,729674955885271,0" user="细水长流">[赞][赞][赞]</d>
<d p="15.74,1,24,7154951369349139237,1665895089835,0,103285851150,0" user="小结">点关注哦！别把娜娜弄丢了</d>
<d p="15.75,1,24,7154951369349139237,1665895089850,0,3576032455832312,0" user="庄稼医生">昊艺太像演员吴磊了</d>
<d p="16.12,1,24,7154951369349139237,1665895090219,0,782451517168620,0" user="九歌">[赞][赞][赞][赞][赞]</d>
<d p="16.13,1,24,7154951369349139237,1665895090226,0,98160055144,0" user="箱包">小牛优秀优秀了</d>
<gift ts="16.18" user="空姐走秀" giftname="小心心" giftcount="6"></gift>
<d p="16.92,1,24,7154951369349139237,1665895091021,0,108131197116,0" user="依然">娜娜咪呢？娜娜咪呢？娜娜咪呢？娜娜咪呢？娜娜咪呢？娜娜咪呢？娜娜咪呢？娜娜咪呢？娜娜咪呢？娜娜咪呢？</d>
<gift ts="16.93" user="空姐走秀" giftname="小心心" giftcount="1"></gift>
<d p="17.13,1,24,7154951369349139237,1665895091224,0,69559435453,0" user="Sunmoon">优秀优秀优秀</d>
<d p="17.15,1,24,7154951369349139237,1665895091246,0,103911534126,0" user="美美">帅艺艺[呲牙][呲牙][呲牙]</d>
<gift ts="17.33" user="~情天～" giftname="小心心" giftcount="1"></gift>
<gift ts="17.33" user="有故事，也有酒" giftname="小心心" giftcount="1"></gift>
<d p="17.36,1,24,7154951369349139237,1665895091457,0,93431411941,0" user="LOVE BABY">昊艺很聪明，情商很高，加油！</d>
<d p="17.60,1,24,7154951369349139237,1665895091701,0,430628488619486,0" user="※≈北极星辰≈※">志成 幸福，这多小姐姐陪</d>
<d p="17.94,1,24,7154951369349139237,1665895092034,0,3681585956917981,0" user="奇闻异事">最爱昊艺 昊艺最帅</d>
<gift ts="18.35" user="空姐走秀" giftname="小心心" giftcount="2"></gift>
<d p="19.33,1,24,7154951369349139237,1665895093432,0,73164585940,0" user="西奈_川川子">志成加油</d>
<gift ts="19.74" user="zhouliying" giftname="小心心" giftcount="1"></gift>
<d p="19.94,1,24,7154951369349139237,1665895094041,0,111040015716,0" user="用户6816529794994">小牛最好</d>
<gift ts="20.14" user="空姐走秀" giftname="小心心" giftcount="3"></gift>
<gift ts="20.15" user="有故事，也有酒" giftname="小心心" giftcount="1"></gift>
<gift ts="20.54" user="zhouliying" giftname="小心心" giftcount="4"></gift>
<gift ts="20.55" user="~情天～" giftname="小心心" giftcount="1"></gift>
<d p="20.83,1,24,7154951369349139237,1665895094930,0,99248299809,0" user="Dan">昊艺帅</d>
<gift ts="20.87" user="用户2487897295191" giftname="小心心" giftcount="1"></gift>
<d p="21.19,1,24,7154951369349139237,1665895095287,0,3623624944658925,0" user="刘七">帅哥美女如云都美</d>
<gift ts="21.20" user="丁玲" giftname="棒棒糖" giftcount="1"></gift>
<d p="21.21,1,24,7154951369349139237,1665895095312,0,105463915623,0" user="用户9674901204264">女漂亮男帅气</d>
<d p="21.22,1,24,7154951369349139237,1665895095318,0,3562866467677047,0" user="~情天～">点关注哦！别把娜娜弄丢了</d>
<gift ts="21.62" user="有故事，也有酒" giftname="小心心" giftcount="1"></gift>
<gift ts="21.79" user="酒帝" giftname="" giftcount="1"></gift>
<gift ts="21.80" user="空姐走秀" giftname="小心心" giftcount="4"></gift>
<d p="21.83,1,24,7154951369349139237,1665895095931,0,105009193231,0" user="走一走，转一转">点关注哦！别把娜娜弄丢了</d>
<d p="22.62,1,24,7154951369349139237,1665895096719,0,105116877933,0" user="抖擞人生">志成[赞][赞][赞]</d>
<d p="22.79,1,24,7154951369349139237,1665895096892,0,3531237609440990,0" user="琳晴钰">交朋友交朋友交朋友交朋友交朋友交朋友交朋友交朋友交朋友交朋友</d>
<d p="23.39,1,24,7154951369349139237,1665895097491,0,101288813086,0" user="东">你们团队还要增加人员吗</d>
<gift ts="23.40" user="zhouliying" giftname="小心心" giftcount="4"></gift>
<gift ts="23.41" user="用户2487897295191" giftname="小心心" giftcount="1"></gift>
<gift ts="23.42" user="空姐走秀" giftname="小心心" giftcount="5"></gift>
<gift ts="23.44" user="丁玲" giftname="棒棒糖" giftcount="1"></gift>
<gift ts="24.80" user="富到平安" giftname="小心心" giftcount="1"></gift>
<gift ts="24.81" user="有故事，也有酒" giftname="小心心" giftcount="1"></gift>
<gift ts="24.82" user="无悔" giftname="小心心" giftcount="1"></gift>
<d p="25.01,1,24,7154951369349139237,1665895099108,0,4384473629332275,0" user="陈南京房产咨询">娜娜咪带你偷懒[呲牙]</d>
<d p="25.03,1,24,7154951369349139237,1665895099125,0,106915901970,0" user="没有如果">艺艺像吴磊</d>
<gift ts="25.03" user="十" giftname="棒棒糖" giftcount="1"></gift>
<gift ts="25.21" user="空姐走秀" giftname="小心心" giftcount="6"></gift>
<gift ts="25.81" user="方格" giftname="小心心" giftcount="1"></gift>
<d p="26.21,1,24,7154951369349139237,1665895100311,0,93835637987,0" user="阿杜造型">交朋友交朋友交朋友交友交朋友交朋友交朋友交朋友交朋友交朋友交朋友交朋友交朋友交朋友交朋友交朋友交朋友</d>
<gift ts="26.22" user="富到平安" giftname="小心心" giftcount="2"></gift>
<gift ts="26.85" user="空姐走秀" giftname="小心心" giftcount="7"></gift>
<d p="27.31,1,24,7154951369349139237,1665895101412,0,98160055144,0" user="箱包">小牛优秀了优秀了</d>
<d p="27.34,1,24,7154951369349139237,1665895101441,0,110612054062,0" user="孙家姑凉陈家媳妇">点关注哦！别把娜娜弄丢了</d>
<gift ts="27.69" user="十" giftname="棒棒糖" giftcount="1"></gift>
<gift ts="27.71" user="无悔" giftname="小心心" giftcount="1"></gift>
<gift ts="27.88" user="空姐走秀" giftname="小心心" giftcount="8"></gift>
<d p="28.27,1,24,7154951369349139237,1665895102366,0,3646457143892371,0" user="用户4643745180443">小牛优秀</d>
<gift ts="28.29" user="唐唐有点酸" giftname="" giftcount="1"></gift>
<gift ts="28.87" user="方格" giftname="小心心" giftcount="1"></gift>
<gift ts="29.07" user="富到平安" giftname="小心心" giftcount="2"></gift>
<gift ts="29.08" user="空姐走秀" giftname="小心心" giftcount="9"></gift>
<d p="30.29,1,24,7154951369349139237,1665895104392,0,3531237609440990,0" user="琳晴钰">交朋友交朋友交朋友交朋友交朋友交朋友交朋友交朋友交朋友交朋友</d>
<gift ts="30.69" user="空姐走秀" giftname="小心心" giftcount="10"></gift>
<d p="30.89,1,24,7154951369349139237,1665895104992,0,2013895193796476,0" user="艾琳">点关注哦！别把娜娜弄丢了</d>
<d p="31.30,1,24,7154951369349139237,1665895105393,0,2467749307362039,0" user="舒雅『高品质红豆杉酵素浴』">点关注哦！别把娜娜弄丢了</d>
<gift ts="32.12" user="空姐走秀" giftname="小心心" giftcount="11"></gift>
<d p="32.31,1,24,7154951369349139237,1665895106410,0,1094745133686292,0" user="雨后天晴">点关注哦！别把娜娜弄丢了</d>
<gift ts="33.20" user="空姐走秀" giftname="小心心" giftcount="12"></gift>
<gift ts="33.65" user="阿分姐" giftname="小心心" giftcount="1"></gift>
<d p="34.21,1,24,7154951369349139237,1665895108304,0,16187852796,0" user="xiexie">好听</d>
<d p="34.21,1,24,7154951369349139237,1665895108313,0,2115112440695757,0" user="人心所向便是光">好厉害</d>
<d p="34.60,1,24,7154951369349139237,1665895108702,0,659313036638600,0" user="酒帝">点关注哦！别把娜娜弄丢了</d>
<gift ts="34.61" user="空姐走秀" giftname="小心心" giftcount="13"></gift>
<d p="35.01,1,24,7154951369349139237,1665895109106,0,4029053639075964,0" user="春天的大森林">这女的声音不好听</d>
<d p="35.01,1,24,7154951369349139237,1665895109110,0,92941096283,0" user="康丽紫砂">志成</d>
<d p="35.20,1,24,7154951369349139237,1665895109298,0,3531237609440990,0" user="琳晴钰">交朋友交朋友交朋友交朋友交朋友交朋友交朋友交朋友交朋友交朋友</d>
<d p="36.01,1,24,7154951369349139237,1665895110105,0,63545143159,0" user="广州市轩美装饰有限公司">[赞]</d>
<gift ts="36.02" user="阿分姐" giftname="小心心" giftcount="1"></gift>
<gift ts="36.21" user="空姐走秀" giftname="小心心" giftcount="14"></gift>
<d p="37.01,1,24,7154951369349139237,1665895111111,0,108131197116,0" user="依然">娜娜咪呢？娜娜咪呢？娜娜咪呢？娜娜咪呢？娜娜咪呢？娜娜咪呢？娜娜咪呢？娜娜咪呢？娜娜咪呢？娜娜咪呢？</d>
<d p="37.63,1,24,7154951369349139237,1665895111733,0,86737645744,0" user="宝宝妈">志成优秀</d>
<d p="37.66,1,24,7154951369349139237,1665895111762,0,16187852796,0" user="xiexie">好听</d>
<d p="37.82,1,24,7154951369349139237,1665895111921,0,307500560955287,0" user="@笑哈哈">三位帅哥太优秀了[666][666][666][666][666][666][666][666]</d>
<d p="38.04,1,24,7154951369349139237,1665895112136,0,70767539376,0" user="我就喜欢你">昊艺有明星像</d>
<d p="38.86,1,24,7154951369349139237,1665895112960,0,93042110071,0" user="小">志成[鼓掌][鼓掌][鼓掌][鼓掌]</d>
<d p="39.07,1,24,7154951369349139237,1665895113167,0,105463915623,0" user="用户9674901204264">太棒了</d>
<gift ts="39.08" user="空姐走秀" giftname="小心心" giftcount="14"></gift>
<d p="40.00,1,24,7154951369349139237,1665895114100,0,93835637987,0" user="阿杜造型">交朋友交朋友交朋友交友交朋友交朋友交朋友交朋友交朋友交朋友交朋友交朋友交朋友交朋友交朋友交朋友交朋友</d>
<d p="40.83,1,24,7154951369349139237,1665895114932,0,3576032455832312,0" user="庄稼医生">艺艺帅</d>
<gift ts="41.05" user="晨曦" giftname="玫瑰" giftcount="1"></gift>
<d p="41.05,1,24,7154951369349139237,1665895115150,0,93761677650,0" user="影儿月月">志成好听</d>
<d p="41.08,1,24,7154951369349139237,1665895115183,0,1472997175334798,0" user="康乃馨">点关注哦！别把娜娜弄丢了</d>
<d p="41.22,1,24,7154951369349139237,1665895115320,0,3720376423818740,0" user="忆红尘">点关注哦！别把娜娜弄丢了</d>
<gift ts="41.62" user="雨后天晴" giftname="" giftcount="1"></gift>
<d p="41.83,1,24,7154951369349139237,1665895115923,0,68312513889,0" user="NiuL噜噜">[鼓掌][鼓掌][鼓掌][鼓掌][鼓掌][鼓掌]</d>
<gift ts="42.03" user="一米八的乔治" giftname="小心心" giftcount="1"></gift>
<d p="42.04,1,24,7154951369349139237,1665895116135,0,102301320449,0" user="纳尼！">娜娜给榜一点点关注</d>
<d p="42.66,1,24,7154951369349139237,1665895116756,0,3681585956917981,0" user="奇闻异事">最爱昊艺 昊艺最帅</d>
<d p="43.03,1,24,7154951369349139237,1665895117129,0,101389319602,0" user="四处奔波">点关注哦！别把娜娜弄丢了</d>
<gift ts="43.44" user="晨曦" giftname="玫瑰" giftcount="1"></gift>
<d p="43.66,1,24,7154951369349139237,1665895117760,0,100113911309,0" user="可可西里">给小牛点点关注谢谢</d>
<gift ts="43.70" user="空姐走秀" giftname="抖音" giftcount="10"></gift>
<d p="43.84,1,24,7154951369349139237,1665895117941,0,99622060472,0" user="新疆娟姐">男团很优秀[赞][赞][赞]</d>
<d p="44.05,1,24,7154951369349139237,1665895118146,0,2040286895673784,0" user="郝小妞">志成太优秀了，今天太卖力了</d>
<d p="44.06,1,24,7154951369349139237,1665895118158,0,3531237609440990,0" user="琳晴钰">交朋友交朋友交朋友交朋友交朋友交朋友交朋友交朋友交朋友交朋友</d>
<gift ts="44.65" user="芹芹" giftname="入团卡" giftcount="1"></gift>
<gift ts="44.85" user="丁玲" giftname="" giftcount="1"></gift>
<gift ts="45.28" user="一米八的乔治" giftname="小心心" giftcount="1"></gift>
<gift ts="45.48" user="空姐走秀" giftname="抖音" giftcount="11"></gift>
<gift ts="46.16" user="千锤百炼" giftname="小心心" giftcount="1"></gift>
<gift ts="46.76" user="空姐走秀" giftname="抖音" giftcount="12"></gift>
<d p="46.95,1,24,7154951369349139237,1665895121045,0,62376665955,0" user="爱笑的女孩">昊艺把艺陈膀子压到了，就我一个人看到了吗？</d>
<gift ts="47.76" user="芹芹" giftname="入团卡" giftcount="1"></gift>
<gift ts="47.97" user="空姐走秀" giftname="抖音" giftcount="13"></gift>
<gift ts="48.37" user="芹芹" giftname="" giftcount="1"></gift>
<d p="49.18,1,24,7154951369349139237,1665895123282,0,1975148180668907,0" user="巍巍岁月">娜娜搞艺术有才华，比昊瀚还厉害！</d>
<gift ts="49.37" user="千锤百炼" giftname="小心心" giftcount="1"></gift>
<d p="49.61,1,24,7154951369349139237,1665895123710,0,2699996533365133,0" user="文">破音</d>
<d p="49.63,1,24,7154951369349139237,1665895123730,0,4384473629332275,0" user="陈南京房产咨询">画面走一走</d>
<gift ts="49.97" user="空姐走秀" giftname="抖音" giftcount="14"></gift>
<d p="50.18,1,24,7154951369349139237,1665895124277,0,82874388904,0" user="汶谦">志成厉害</d>
<d p="50.98,1,24,7154951369349139237,1665895125078,0,1569722443773389,0" user="李老头">点关注哦！别把娜娜弄丢了</d>
<d p="51.21,1,24,7154951369349139237,1665895125309,0,3681585956917981,0" user="奇闻异事">最爱昊艺 昊艺最帅</d>
<gift ts="51.38" user="空姐走秀" giftname="抖音" giftcount="15"></gift>
<d p="52.02,1,24,7154951369349139237,1665895126120,0,95739864498,0" user="昌华冻品（关注必回）">交朋友交朋友交朋友交朋友交朋友交朋友交朋友交朋友交朋友交朋友交朋友交朋友交朋友交朋友交朋友交朋友交朋</d>
<d p="52.03,1,24,7154951369349139237,1665895126126,0,93183800382,0" user="开心每一天$">志成[赞][赞][赞][赞][赞][赞][赞][赞]</d>
<d p="52.44,1,24,7154951369349139237,1665895126541,0,395438604170743,0" user="牙牙">点关注哦！别把娜娜弄丢了</d>
<gift ts="52.45" user="空姐走秀" giftname="抖音" giftcount="16"></gift>
<d p="52.82,1,24,7154951369349139237,1665895126919,0,108131197116,0" user="依然">娜娜咪呢？娜娜咪呢？娜娜咪呢？娜娜咪呢？娜娜咪呢？娜娜咪呢？娜娜咪呢？娜娜咪呢？娜娜咪呢？娜娜咪呢？</d>
<d p="53.01,1,24,7154951369349139237,1665895127110,0,72656248979,0" user="悄悄（好物分享）">点关注哦！别把娜娜弄丢了</d>
<gift ts="53.25" user="展翅高飞" giftname="" giftcount="1"></gift>
<d p="53.27,1,24,7154951369349139237,1665895127373,0,109463728400,0" user="保持沉默">志成好拼啊</d>
<d p="53.63,1,24,7154951369349139237,1665895127731,0,99266873729,0" user="三餐～四季">求关注交朋友求关注交朋友求关注交朋友</d>
<d p="53.83,1,24,7154951369349139237,1665895127925,0,3316564104058173,0" user="冷冷">小眼睛，志成[赞]</d>
<d p="54.03,1,24,7154951369349139237,1665895128124,0,2612063539311524,0" user="御姐">上二万</d>
<gift ts="54.83" user="空姐走秀" giftname="抖音" giftcount="17"></gift>
<d p="54.84,1,24,7154951369349139237,1665895128938,0,1284680857421885,0" user="四哥">[鼓掌][鼓掌][鼓掌][鼓掌][鼓掌][鼓掌][鼓掌][鼓掌][鼓掌][鼓掌][鼓掌]</d>
<d p="55.53,1,24,7154951369349139237,1665895129625,0,3531237609440990,0" user="琳晴钰">交朋友交朋友交朋友交朋友交朋友交朋友交朋友交朋友交朋友交朋友</d>
<d p="55.54,1,24,7154951369349139237,1665895129635,0,2115112440695757,0" user="人心所向便是光">娜娜是主心骨</d>
<d p="55.67,1,24,7154951369349139237,1665895129769,0,69559435453,0" user="Sunmoon">娜娜</d>
<gift ts="55.84" user="空姐走秀" giftname="抖音" giftcount="18"></gift>
<d p="56.65,1,24,7154951369349139237,1665895130744,0,105116877933,0" user="抖擞人生">娜娜</d>
<d p="56.85,1,24,7154951369349139237,1665895130944,0,94168590273,0" user="程二姐110">艺艺</d>
<d p="56.85,1,24,7154951369349139237,1665895130950,0,53152927371,0" user="香巴熟食">太极拳[赞][捂脸][666][666][玫瑰][玫瑰][玫瑰][玫瑰][玫瑰]</d>
<gift ts="57.27" user="空姐走秀" giftname="抖音" giftcount="19"></gift>
<d p="58.05,1,24,7154951369349139237,1665895132150,0,98415779196,0" user="桂花糕-婧怡">点关注哦！别把娜娜弄丢了</d>
<d p="58.06,1,24,7154951369349139237,1665895132159,0,109628662819,0" user="蓝鯨">志成优秀</d>
<gift ts="58.45" user="空姐走秀" giftname="抖音" giftcount="20"></gift>
<d p="58.49,1,24,7154951369349139237,1665895132593,0,1975148180668907,0" user="巍巍岁月">娜娜搞艺术有才华，比昊瀚还厉害！</d>
<d p="59.12,1,24,7154951369349139237,1665895133220,0,632915741906672,0" user="陈惠、、">苏星肯定也会是王炸</d>
<d p="59.72,1,24,7154951369349139237,1665895133823,0,3394909372954157,0" user="红丫头">都很优秀</d>
<gift ts="59.74" user="空姐走秀" giftname="抖音" giftcount="21"></gift>
<d p="60.13,1,24,7154951369349139237,1665895134224,0,1336608451725632,0" user="过平">都优秀</d>
<d p="60.13,1,24,7154951369349139237,1665895134230,0,96966916250,0" user="用户1708229597470">昊艺要多吃点饭，这样高强工作</d>
<gift ts="60.52" user="菲" giftname="入团卡" giftcount="1"></gift>
<d p="60.55,1,24,7154951369349139237,1665895134646,0,82874388904,0" user="汶谦">娜娜</d>
<d p="60.55,1,24,7154951369349139237,1665895134653,0,95739864498,0" user="昌华冻品（关注必回）">交朋友交朋友交朋友交朋友交朋友交朋友交朋友交朋友交朋友交朋友交朋友交朋友交朋友交朋友交朋友交朋友交朋</d>
<gift ts="60.76" user="空姐走秀" giftname="抖音" giftcount="22"></gift>
<d p="61.15,1,24,7154951369349139237,1665895135243,0,73164585940,0" user="西奈_川川子">艺艺[捂脸][捂脸][捂脸][捂脸]</d>
<gift ts="61.55" user="惠姐" giftname="小心心" giftcount="1"></gift>
<d p="61.57,1,24,7154951369349139237,1665895135664,0,106915901970,0" user="没有如果">艺艺脑子好用</d>
<gift ts="61.76" user="曹家八姐" giftname="小心心" giftcount="1"></gift>
<d p="61.77,1,24,7154951369349139237,1665895135865,0,93761677650,0" user="影儿月月">志成加油</d>
<d p="61.95,1,24,7154951369349139237,1665895136050,0,4226168305752471,0" user="爱酷就运动">昊艺</d>
<d p="61.96,1,24,7154951369349139237,1665895136057,0,99010349140,0" user="一生有你">上3万</d>
<gift ts="61.96" user="空姐走秀" giftname="抖音" giftcount="23"></gift>
<d p="62.35,1,24,7154951369349139237,1665895136452,0,92625580361,0" user="kylie">点关注哦！别把娜娜弄丢了</d>
<gift ts="62.77" user="空姐走秀" giftname="抖音" giftcount="24"></gift>
<gift ts="62.96" user="菲" giftname="入团卡" giftcount="1"></gift>
<d p="63.36,1,24,7154951369349139237,1665895137462,0,110860957499,0" user="简单0102">小牛也很棒 发展潜力很大 加油</d>
<gift ts="63.38" user="宜宜奶" giftname="小心心" giftcount="1"></gift>
<gift ts="63.59" user="天蝎座" giftname="小心心" giftcount="1"></gift>
<gift ts="63.78" user="空姐走秀" giftname="抖音" giftcount="25"></gift>
<gift ts="64.18" user="惠姐" giftname="小心心" giftcount="1"></gift>
<d p="64.19,1,24,7154951369349139237,1665895138285,0,1891590424757646,0" user="用户7854323537011">昊艺</d>
<d p="64.38,1,24,7154951369349139237,1665895138482,0,2207438581531703,0" user="追梦人123">人才娜娜米[赞]</d>
<gift ts="64.39" user="曹家八姐" giftname="小心心" giftcount="1"></gift>
<d p="64.40,1,24,7154951369349139237,1665895138499,0,3681585956917981,0" user="奇闻异事">最爱昊艺 昊艺最帅</d>
<d p="64.58,1,24,7154951369349139237,1665895138682,0,80778542111,0" user="HPB">艺艺在偷懒[捂脸]</d>
<d p="64.61,1,24,7154951369349139237,1665895138706,0,85840261774,0" user="小岳阳">这是开车吗？猛打方向盘啊</d>
<gift ts="65.31" user="空姐走秀" giftname="抖音" giftcount="26"></gift>
<gift ts="65.32" user="小平" giftname="小心心" giftcount="1"></gift>
<gift ts="65.92" user="菲" giftname="" giftcount="1"></gift>
<gift ts="65.94" user="空姐走秀" giftname="抖音" giftcount="27"></gift>
<gift ts="66.11" user="天蝎座" giftname="小心心" giftcount="1"></gift>
<d p="66.52,1,24,7154951369349139237,1665895140617,0,3553243437472766,0" user="鱼的记忆">不错</d>
<gift ts="66.52" user="宜宜奶" giftname="小心心" giftcount="1"></gift>
<d p="66.53,1,24,7154951369349139237,1665895140626,0,303879504010253,0" user="抹茶味儿的菇凉">昊艺[捂脸]</d>
<d p="66.53,1,24,7154951369349139237,1665895140631,0,3531237609440990,0" user="琳晴钰">交朋友交朋友交朋友交朋友交朋友交朋友交朋友交朋友交朋友交朋友</d>
<d p="66.72,1,24,7154951369349139237,1665895140813,0,3711598750865184,0" user="晓玲玲">点关注哦！别把娜娜弄丢了</d>
<gift ts="66.91" user="空姐走秀" giftname="抖音" giftcount="28"></gift>
<d p="67.11,1,24,7154951369349139237,1665895141212,0,92757487433,0" user="星星星星星">小牛在榜5点点关注谢谢</d>
<gift ts="67.72" user="空姐走秀" giftname="抖音" giftcount="29"></gift>
<d p="67.93,1,24,7154951369349139237,1665895142024,0,3394909372954157,0" user="红丫头">太美哒</d>
<d p="67.93,1,24,7154951369349139237,1665895142029,0,3021054335518620,0" user="四川绵阳17">小牛，紫宸好听</d>
<gift ts="68.53" user="小平" giftname="小心心" giftcount="1"></gift>
<d p="68.54,1,24,7154951369349139237,1665895142635,0,61493384985,0" user="惠小慧">点关注哦！别把娜娜弄丢了</d>
<d p="68.72,1,24,7154951369349139237,1665895142821,0,104917173590,0" user="淘淘">点关注哦！别把娜娜弄丢了</d>
<d p="69.15,1,24,7154951369349139237,1665895143247,0,95739864498,0" user="昌华冻品（关注必回）">交朋友交朋友交朋友交朋友交朋友交朋友交朋友交朋友交朋友交朋友交朋友交朋友交朋友交朋友交朋友交朋友交朋</d>
<gift ts="69.16" user="空姐走秀" giftname="抖音" giftcount="30"></gift>
<d p="69.17,1,24,7154951369349139237,1665895143264,0,96618626400,0" user="秋秋">太棒了[比心][比心][比心][比心]</d>
<d p="69.58,1,24,7154951369349139237,1665895143678,0,2383367290227992,0" user="天蝎座">点关注哦！别把娜娜弄丢了</d>
<gift ts="69.59" user="空姐走秀" giftname="抖音" giftcount="31"></gift>
<d p="69.74,1,24,7154951369349139237,1665895143833,0,2533699936584392,0" user="宜宜奶">[赞][赞][赞][赞][赞][赞][赞][赞][赞][赞]</d>
<d p="70.14,1,24,7154951369349139237,1665895144241,0,108699399756,0" user="冰糖橙">上2万</d>
<gift ts="70.57" user="空姐走秀" giftname="抖音" giftcount="32"></gift>
<d p="70.95,1,24,7154951369349139237,1665895145046,0,53152927371,0" user="香巴熟食">太极拳[赞][赞][捂脸][捂脸][玫瑰][玫瑰][666][666][666][666][666][666]</d>
<d p="71.15,1,24,7154951369349139237,1665895145245,0,82874388904,0" user="汶谦">志成优秀</d>
<d p="71.15,1,24,7154951369349139237,1665895145251,0,10687694380,0" user="因爲在乎゛ォ荟亂想">腋下</d>
<gift ts="71.35" user="空姐走秀" giftname="抖音" giftcount="33"></gift>
<gift ts="72.40" user="空姐走秀" giftname="抖音" giftcount="34"></gift>
<d p="72.41,1,24,7154951369349139237,1665895146503,0,2704452706384232,0" user="A小凳子">三个帅哥不错</d>
<d p="72.60,1,24,7154951369349139237,1665895146700,0,110580670189,0" user="薇薇">怎么不见苏阳</d>
<d p="73.00,1,24,7154951369349139237,1665895147102,0,96431721334,0" user="森林兄弟">志成优秀</d>
<gift ts="73.20" user="雪绒花" giftname="小心心" giftcount="1"></gift>
<d p="73.22,1,24,7154951369349139237,1665895147319,0,104262404136,0" user="记得自己">点关注哦！别把娜娜弄丢了</d>
<gift ts="73.80" user="空姐走秀" giftname="抖音" giftcount="35"></gift>
<gift ts="74.40" user="空姐走秀" giftname="抖音" giftcount="36"></gift>
<d p="74.44,1,24,7154951369349139237,1665895148534,0,3681585956917981,0" user="奇闻异事">最爱昊艺 昊艺最帅</d>
<gift ts="74.44" user="木木" giftname="小心心" giftcount="1"></gift>
<d p="74.80,1,24,7154951369349139237,1665895148897,0,70767539376,0" user="我就喜欢你">好听</d>
<gift ts="74.80" user="宜宜奶" giftname="小心心" giftcount="1"></gift>
<d p="75.01,1,24,7154951369349139237,1665895149108,0,2977098613402040,0" user="今飞西比">娜娜咪偷[捂脸][捂脸][捂脸][捂脸][捂脸]</d>
<gift ts="75.61" user="空姐走秀" giftname="抖音" giftcount="37"></gift>
<gift ts="75.64" user="伟达" giftname="小心心" giftcount="1"></gift>
<d p="75.65,1,24,7154951369349139237,1665895149746,0,84348743793,0" user="冰">点关注哦！别把娜娜弄丢了</d>
<gift ts="75.81" user="雪绒花" giftname="小心心" giftcount="1"></gift>
<gift ts="76.04" user="圣光天马" giftname="小心心" giftcount="1"></gift>
<d p="76.04,1,24,7154951369349139237,1665895150140,0,111313542791,0" user="资本家">天天就是这几首[捂脸][捂脸][捂脸][捂脸][捂脸]</d>
<d p="76.05,1,24,7154951369349139237,1665895150146,0,3531237609440990,0" user="琳晴钰">交朋友交朋友交朋友交朋友交朋友交朋友交朋友交朋友交朋友交朋友</d>
<gift ts="76.42" user="空姐走秀" giftname="抖音" giftcount="38"></gift>
<gift ts="76.64" user="胡梦菲" giftname="入团卡" giftcount="1"></gift>
<gift ts="76.82" user="富到平安" giftname="小心心" giftcount="1"></gift>
<d p="76.83,1,24,7154951369349139237,1665895150925,0,2664828779373287,0" user="好像风动了.">点关注哦！别把娜娜弄丢了</d>
<gift ts="77.02" user="空姐走秀" giftname="抖音" giftcount="39"></gift>
<gift ts="77.03" user="木木" giftname="小心心" giftcount="1"></gift>
<gift ts="77.42" user="宜宜奶" giftname="小心心" giftcount="1"></gift>
<gift ts="77.42" user="胡斌" giftname="小心心" giftcount="1"></gift>
<d p="77.64,1,24,7154951369349139237,1665895151733,0,95739864498,0" user="昌华冻品（关注必回）">交朋友交朋友交朋友交朋友交朋友交朋友交朋友交朋友交朋友交朋友交朋友交朋友交朋友交朋友交朋友交朋友交朋</d>
<gift ts="77.83" user="空姐走秀" giftname="抖音" giftcount="40"></gift>
<gift ts="78.20" user="无～情。。。" giftname="小心心" giftcount="1"></gift>
<gift ts="78.40" user="伟达" giftname="小心心" giftcount="1"></gift>
<d p="78.41,1,24,7154951369349139237,1665895152509,0,102921537609,0" user="伟达">点关注哦！别把娜娜弄丢了</d>
<gift ts="78.60" user="圣光天马" giftname="小心心" giftcount="1"></gift>
<gift ts="79.03" user="空姐走秀" giftname="抖音" giftcount="41"></gift>
<d p="79.03,1,24,7154951369349139237,1665895153133,0,70767539376,0" user="我就喜欢你">好听</d>
<gift ts="79.61" user="胡梦菲" giftname="入团卡" giftcount="1"></gift>
<gift ts="79.61" user="空姐走秀" giftname="抖音" giftcount="42"></gift>
<gift ts="79.62" user="富到平安" giftname="小心心" giftcount="1"></gift>
<gift ts="80.02" user="胡斌" giftname="小心心" giftcount="1"></gift>
<gift ts="80.43" user="空姐走秀" giftname="抖音" giftcount="43"></gift>
<d p="80.50,1,24,7154951369349139237,1665895154601,0,100683352735,0" user="玲玲">点关注哦！别把娜娜弄丢了</d>
<gift ts="80.82" user="顾大爷" giftname="小心心" giftcount="1"></gift>
<gift ts="81.24" user="无～情。。。" giftname="小心心" giftcount="1"></gift>
<gift ts="81.44" user="空姐走秀" giftname="抖音" giftcount="44"></gift>
<d p="81.44,1,24,7154951369349139237,1665895155542,0,96618626400,0" user="秋秋">艺艺帅帅帅</d>
<gift ts="81.47" user="空姐走秀" giftname="抖音" giftcount="45"></gift>
<d p="81.47,1,24,7154951369349139237,1665895155572,0,4384473629332275,0" user="陈南京房产咨询">昊艺偷懒[呲牙]</d>
<d p="81.49,1,24,7154951369349139237,1665895155587,0,2853953637202775,0" user="峰回路转">都很给力[比心]</d>
<d p="81.50,1,24,7154951369349139237,1665895155602,0,82874388904,0" user="汶谦">志成优秀</d>
<d p="81.85,1,24,7154951369349139237,1665895155948,0,3531237609440990,0" user="琳晴钰">交朋友交朋友交朋友交朋友交朋友交朋友交朋友交朋友交朋友交朋友</d>
<gift ts="81.86" user="空姐走秀" giftname="抖音" giftcount="46"></gift>
<gift ts="82.04" user="空姐走秀" giftname="抖音" giftcount="47"></gift>
<d p="82.05,1,24,7154951369349139237,1665895156149,0,3038665937268811,0" user="这条河叫时光">点关注哦！别把娜娜弄丢了</d>
<d p="82.66,1,24,7154951369349139237,1665895156762,0,8644602272,0" user="好久不见！">娜娜</d>
<gift ts="82.87" user="空姐走秀" giftname="抖音" giftcount="48"></gift>
<d p="83.27,1,24,7154951369349139237,1665895157369,0,109314433427,0" user="胡梦菲">点关注哦！别把娜娜弄丢了</d>
<gift ts="83.28" user="玲玲" giftname="" giftcount="1"></gift>
<gift ts="83.30" user="顾大爷" giftname="小心心" giftcount="1"></gift>
<gift ts="83.32" user="空姐走秀" giftname="抖音" giftcount="49"></gift>
<d p="83.71,1,24,7154951369349139237,1665895157806,0,102157790189,0" user="恋上1993">志成优秀</d>
<d p="83.88,1,24,7154951369349139237,1665895157973,0,92757487433,0" user="星星星星星">小牛点点关注谢谢</d>
<gift ts="84.43" user="空姐走秀" giftname="抖音" giftcount="50"></gift>
<gift ts="84.80" user="空姐走秀" giftname="抖音" giftcount="51"></gift>
<gift ts="85.01" user="空姐走秀" giftname="小心心" giftcount="1"></gift>
<gift ts="85.02" user="空姐走秀" giftname="抖音" giftcount="52"></gift>
<gift ts="85.65" user="空姐走秀" giftname="抖音" giftcount="53"></gift>
<d p="85.67,1,24,7154951369349139237,1665895159768,0,70767539376,0" user="我就喜欢你">好听</d>
<gift ts="85.67" user="好像风动了." giftname="" giftcount="1"></gift>
<gift ts="85.68" user="空姐走秀" giftname="抖音" giftcount="54"></gift>
<d p="85.70,1,24,7154951369349139237,1665895159798,0,101708274005,0" user="甲骨文">点关注哦！别把娜娜弄丢了</d>
<d p="85.81,1,24,7154951369349139237,1665895159906,0,95739864498,0" user="昌华冻品（关注必回）">交朋友交朋友交朋友交朋友交朋友交朋友交朋友交朋友交朋友交朋友交朋友交朋友交朋友交朋友交朋友交朋友交朋</d>
<d p="85.81,1,24,7154951369349139237,1665895159912,0,3681585956917981,0" user="奇闻异事">最爱昊艺 昊艺最帅</d>
<gift ts="85.82" user="无～情。。。" giftname="小心心" giftcount="1"></gift>
<d p="86.21,1,24,7154951369349139237,1665895160304,0,108131197116,0" user="依然">娜娜咪呢？娜娜咪呢？娜娜咪呢？娜娜咪呢？娜娜咪呢？娜娜咪呢？娜娜咪呢？娜娜咪呢？娜娜咪呢？娜娜咪呢？</d>
<d p="86.41,1,24,7154951369349139237,1665895160505,0,110424299797,0" user="签约">娜娜凶艺艺恨铁不成钢的感觉。</d>
<gift ts="86.62" user="空姐走秀" giftname="小心心" giftcount="2"></gift>
<d p="86.64,1,24,7154951369349139237,1665895160740,0,3531237609440990,0" user="琳晴钰">交朋友交朋友交朋友交朋友交朋友交朋友交朋友交朋友交朋友交朋友</d>
<gift ts="86.81" user="空姐走秀" giftname="抖音" giftcount="55"></gift>
<gift ts="87.21" user="无～情。。。" giftname="小心心" giftcount="2"></gift>
<gift ts="87.63" user="空姐走秀" giftname="抖音" giftcount="56"></gift>
<gift ts="88.02" user="玲玲" giftname="小心心" giftcount="1"></gift>
<gift ts="88.22" user="手机用户63214196341" giftname="小心心" giftcount="1"></gift>
<gift ts="88.23" user="空姐走秀" giftname="小心心" giftcount="3"></gift>
<d p="88.44,1,24,7154951369349139237,1665895162537,0,106915901970,0" user="没有如果">娜娜会带人</d>
<gift ts="88.46" user="富到平安" giftname="抖音" giftcount="1"></gift>
<gift ts="88.62" user="无～情。。。" giftname="小心心" giftcount="3"></gift>
<d p="88.63,1,24,7154951369349139237,1665895162728,0,2752791556400558,0" user="摩羯座">今天状态都好</d>
<gift ts="88.63" user="空姐走秀" giftname="抖音" giftcount="57"></gift>
<gift ts="89.03" user="空姐走秀" giftname="抖音" giftcount="58"></gift>
<d p="89.23,1,24,7154951369349139237,1665895163324,0,1975148180668907,0" user="巍巍岁月">娜娜搞艺术有才华，比昊瀚还厉害！</d>
<gift ts="89.24" user="草根艺人" giftname="入团卡" giftcount="1"></gift>
<gift ts="89.25" user="无～情。。。" giftname="小心心" giftcount="4"></gift>
<gift ts="89.83" user="空姐走秀" giftname="抖音" giftcount="59"></gift>
<gift ts="90.03" user="空姐走秀" giftname="小心心" giftcount="4"></gift>
<d p="90.50,1,24,7154951369349139237,1665895164596,0,3923501883328763,0" user="拥护政府">点关注哦！别把娜娜弄丢了</d>
<gift ts="90.87" user="玲玲" giftname="小心心" giftcount="1"></gift>
<gift ts="90.88" user="手机用户63214196341" giftname="小心心" giftcount="1"></gift>
<gift ts="91.24" user="富到平安" giftname="抖音" giftcount="1"></gift>
<gift ts="91.26" user="空姐走秀" giftname="抖音" giftcount="60"></gift>
<gift ts="91.67" user="空姐走秀" giftname="小心心" giftcount="5"></gift>
<d p="91.71,1,24,7154951369349139237,1665895165808,0,100753295999,0" user="苏州爷">好听！</d>
<gift ts="92.05" user="花开有声" giftname="小心心" giftcount="1"></gift>
<gift ts="92.06" user="草根艺人" giftname="" giftcount="1"></gift>
<gift ts="92.06" user="草根艺人" giftname="入团卡" giftcount="1"></gift>
<d p="92.27,1,24,7154951369349139237,1665895166368,0,3531237609440990,0" user="琳晴钰">交朋友交朋友交朋友交朋友交朋友交朋友交朋友交朋友交朋友交朋友</d>
<gift ts="92.28" user="无～情。。。" giftname="小心心" giftcount="4"></gift>
<d p="93.07,1,24,7154951369349139237,1665895167171,0,21755917100,0" user="怡艺">今天状态太屿了</d>
<gift ts="93.08" user="空姐走秀" giftname="小心心" giftcount="6"></gift>
<gift ts="93.09" user="薛晋" giftname="小心心" giftcount="1"></gift>
<d p="93.46,1,24,7154951369349139237,1665895167561,0,97105188719,0" user="半边天">男士增高鞋挺好看</d>
<d p="93.87,1,24,7154951369349139237,1665895167972,0,111344377721,0" user="华">点关注哦！别把娜娜弄丢了</d>
<gift ts="94.27" user="空姐走秀" giftname="抖音" giftcount="60"></gift>
<d p="94.48,1,24,7154951369349139237,1665895168575,0,3681585956917981,0" user="奇闻异事">最爱昊艺 昊艺最帅</d>
<gift ts="94.49" user="静想天地" giftname="小心心" giftcount="1"></gift>
<gift ts="94.49" user="安娜" giftname="" giftcount="1"></gift>
<gift ts="94.51" user="花开有声" giftname="小心心" giftcount="1"></gift>
<gift ts="94.52" user="富到平安" giftname="舞鞋" giftcount="1"></gift>
<gift ts="94.68" user="空姐走秀" giftname="小心心" giftcount="7"></gift>
<d p="94.87,1,24,7154951369349139237,1665895168969,0,104997836193,0" user="幸福快乐">[玫瑰][玫瑰][玫瑰][玫瑰][玫瑰][玫瑰][玫瑰][玫瑰][玫瑰]</d>
<d p="95.27,1,24,7154951369349139237,1665895169371,0,910040001685405,0" user="用户1588039520691萌萌哒">太好听好听好听好听好听好听好听</d>
<gift ts="95.68" user="薛晋" giftname="小心心" giftcount="1"></gift>
<d p="96.08,1,24,7154951369349139237,1665895170177,0,108131197116,0" user="依然">娜娜咪呢？娜娜咪呢？娜娜咪呢？娜娜咪呢？娜娜咪呢？娜娜咪呢？娜娜咪人了吗</d>
<gift ts="96.28" user="空姐走秀" giftname="小心心" giftcount="8"></gift>
<d p="96.28,1,24,7154951369349139237,1665895170379,0,70767539376,0" user="我就喜欢你">好看</d>
<d p="96.29,1,24,7154951369349139237,1665895170384,0,96431721334,0" user="森林兄弟">给志成点关注</d>
<gift ts="96.67" user="静想天地" giftname="小心心" giftcount="1"></gift>
<d p="97.08,1,24,7154951369349139237,1665895171177,0,85141422258,0" user="薛晋">点关注哦！别把娜娜弄丢了</d>
<gift ts="97.34" user="空姐走秀" giftname="小心心" giftcount="9"></gift>
<gift ts="97.69" user="富到平安" giftname="舞鞋" giftcount="1"></gift>
<d p="97.86,1,24,7154951369349139237,1665895171962,0,2815179683535886,0" user="清风绕指柔">[玫瑰][玫瑰][玫瑰][玫瑰][玫瑰][赞][赞][赞][赞]</d>
<d p="97.88,1,24,7154951369349139237,1665895171974,0,3531237609440990,0" user="琳晴钰">交朋友交朋友交朋友交朋友交朋友交朋友交朋友交朋友交朋友交朋友</d>
<gift ts="98.08" user="光头大叔" giftname="入团卡" giftcount="1"></gift>
<gift ts="98.47" user="用户7274190432866" giftname="小心心" giftcount="1"></gift>
<d p="99.28,1,24,7154951369349139237,1665895173382,0,1754457292941179,0" user="卍阿帅卍">昊艺优秀</d>
<gift ts="99.48" user="空姐走秀" giftname="小心心" giftcount="10"></gift>
<d p="99.68,1,24,7154951369349139237,1665895173774,0,96966916250,0" user="用户1708229597470">昊艺[赞][赞]</d>
<gift ts="100.52" user="光头大叔" giftname="入团卡" giftcount="1"></gift>
<gift ts="101.09" user="光头大叔" giftname="" giftcount="1"></gift>
<gift ts="101.49" user="空姐走秀" giftname="小心心" giftcount="11"></gift>
<d p="101.53,1,24,7154951369349139237,1665895175629,0,70767539376,0" user="我就喜欢你">好听</d>
<gift ts="101.55" user="用户7274190432866" giftname="小心心" giftcount="1"></gift>
<d p="102.12,1,24,7154951369349139237,1665895176221,0,4234940036680263,0" user="Yxs">这声音吓屎</d>
<d p="102.50,1,24,7154951369349139237,1665895176602,0,71910199933,0" user="yang杨">志成志成加油</d>
<gift ts="102.53" user="何何" giftname="小心心" giftcount="1"></gift>
<gift ts="102.90" user="飞" giftname="小心心" giftcount="1"></gift>
<gift ts="102.91" user="狗比人忠" giftname="小心心" giftcount="1"></gift>
<gift ts="102.92" user="二哥" giftname="入团卡" giftcount="1"></gift>
<d p="103.12,1,24,7154951369349139237,1665895177216,0,2084304750915084,0" user="深海">点关注哦！别把娜娜弄丢了</d>
<gift ts="103.93" user="空姐走秀" giftname="小心心" giftcount="12"></gift>
<d p="104.14,1,24,7154951369349139237,1665895178239,0,3531237609440990,0" user="琳晴钰">交朋友交朋友交朋友交朋友交朋友交朋友交朋友交朋友交朋友交朋友</d>
<gift ts="104.75" user="空姐走秀" giftname="小心心" giftcount="13"></gift>
<d p="104.76,1,24,7154951369349139237,1665895178855,0,68312513889,0" user="NiuL噜噜">志成棒棒哒。好听好听[鼓掌][鼓掌][鼓掌][赞][赞][赞][赞][赞][赞]</d>
<gift ts="104.94" user="何何" giftname="小心心" giftcount="1"></gift>
<gift ts="104.96" user="二哥" giftname="入团卡" giftcount="1"></gift>
<gift ts="105.35" user="狗比人忠" giftname="小心心" giftcount="1"></gift>
<d p="105.35,1,24,7154951369349139237,1665895179450,0,93042110071,0" user="小">[鼓掌][鼓掌][鼓掌][鼓掌][鼓掌][鼓掌][鼓掌]志成</d>
<d p="105.55,1,24,7154951369349139237,1665895179643,0,1222273346055640,0" user="雪绒花">好听好听</d>
<gift ts="105.65" user="飞" giftname="小心心" giftcount="1"></gift>
<gift ts="106.36" user="空姐走秀" giftname="小心心" giftcount="14"></gift>
<gift ts="106.76" user="浩荡起航" giftname="" giftcount="1"></gift>
<d p="107.38,1,24,7154951369349139237,1665895181474,0,276683307358312,0" user="安然">艺艺好也是你，不好也是你，说明他们喜欢你</d>
<gift ts="107.97" user="狗比人忠" giftname="小心心" giftcount="1"></gift>
<gift ts="107.98" user="空姐走秀" giftname="小心心" giftcount="15"></gift>
<d p="108.36,1,24,7154951369349139237,1665895182463,0,3553243437472766,0" user="鱼的记忆">努力的主播</d>
<d p="108.58,1,24,7154951369349139237,1665895182681,0,78042630059,0" user="高长菊">[赞][赞][赞][赞][赞][赞][赞][赞][赞][赞]</d>
<d p="108.59,1,24,7154951369349139237,1665895182686,0,1591715329223032,0" user="～单纯～">好听</d>
<gift ts="109.18" user="**华哥：" giftname="入团卡" giftcount="1"></gift>
<d p="109.19,1,24,7154951369349139237,1665895183287,0,3531237609440990,0" user="琳晴钰">交朋友交朋友交朋友交朋友交朋友交朋友交朋友交朋友交朋友交朋友</d>
<d p="109.20,1,24,7154951369349139237,1665895183294,0,103188668795,0" user="樊凡">真好听</d>
<gift ts="109.38" user="空姐走秀" giftname="小心心" giftcount="16"></gift>
<gift ts="109.86" user="谭林" giftname="小心心" giftcount="1"></gift>
<gift ts="109.88" user="狗比人忠" giftname="小心心" giftcount="3"></gift>
<d p="110.46,1,24,7154951369349139237,1665895184555,0,2735222300083165,0" user="美丽幸福绽放">这歌好听比以前的歌好多了</d>
<gift ts="110.48" user="用户6618527670554" giftname="玫瑰" giftcount="1"></gift>
<d p="110.87,1,24,7154951369349139237,1665895184967,0,3589240663052363,0" user="笑忘书">志成[赞][赞][赞][赞]</d>
<gift ts="110.88" user="谭林" giftname="小心心" giftcount="2"></gift>
<gift ts="111.06" user="空姐走秀" giftname="小心心" giftcount="17"></gift>
<gift ts="111.07" user="快乐" giftname="" giftcount="1"></gift>
<gift ts="111.26" user="玲姐" giftname="入团卡" giftcount="1"></gift>
<d p="111.27,1,24,7154951369349139237,1665895185367,0,58890487069,0" user="小考拉">点关注哦！别把娜娜弄丢了</d>
<d p="111.29,1,24,7154951369349139237,1665895185385,0,4344908294660367,0" user="周二姐">好听</d>
<gift ts="111.50" user="谭林" giftname="小心心" giftcount="3"></gift>
<d p="111.86,1,24,7154951369349139237,1665895185962,0,92757487433,0" user="星星星星星">小牛在榜5点点关注谢谢</d>
<d p="111.87,1,24,7154951369349139237,1665895185967,0,773655176939246,0" user="用户9569800493364">志诚优秀</d>
<gift ts="112.06" user="**华哥：" giftname="入团卡" giftcount="1"></gift>
<gift ts="112.27" user="何何" giftname="小心心" giftcount="1"></gift>
<gift ts="112.27" user="穿越时空" giftname="小心心" giftcount="1"></gift>
<gift ts="112.28" user="谭林" giftname="小心心" giftcount="4"></gift>
<gift ts="112.69" user="空姐走秀" giftname="小心心" giftcount="18"></gift>
<d p="112.89,1,24,7154951369349139237,1665895186984,0,101148728031,0" user="嘟嘟宝贝">[鼓掌][鼓掌][鼓掌][鼓掌][鼓掌][赞][赞][赞][赞][赞][赞][赞][赞][赞][赞][赞][赞][赞][赞][赞][感谢][一起加油][一起加油][一起加油][一起加油][一起加油][一起加油][一起加油][一起加油][一起加油][一起加油][一起加油][一起加油][一起加油][一起加油][鼓掌]</d>
<gift ts="113.08" user="狗比人忠" giftname="小心心" giftcount="3"></gift>
<d p="113.10,1,24,7154951369349139237,1665895187201,0,93761677650,0" user="影儿月月">志成优秀</d>
<d p="113.27,1,24,7154951369349139237,1665895187369,0,2428174373487662,0" user="水到渠成">点关注哦！别把娜娜弄丢了</d>
<d p="113.28,1,24,7154951369349139237,1665895187376,0,95739864498,0" user="昌华冻品（关注必回）">交友交朋友交朋友交朋友交朋友交朋友交朋友交朋友交朋友交朋友交朋友交朋友交朋友交朋友交朋友交朋友交朋友</d>
<d p="113.30,1,24,7154951369349139237,1665895187398,0,102934649207,0" user="阿唐">娜娜咩在偷懒</d>
<gift ts="113.70" user="空姐走秀" giftname="小心心" giftcount="19"></gift>
<d p="113.73,1,24,7154951369349139237,1665895187833,0,60348036324,0" user="蜜豆">志车好优秀优秀优秀[鼓掌][鼓掌][鼓掌]</d>
<gift ts="113.74" user="用户6618527670554" giftname="玫瑰" giftcount="1"></gift>
<d p="114.09,1,24,7154951369349139237,1665895188189,0,3681585956917981,0" user="奇闻异事">最爱昊艺 昊艺最帅</d>
<gift ts="114.48" user="玲姐" giftname="入团卡" giftcount="1"></gift>
<d p="114.49,1,24,7154951369349139237,1665895188585,0,105116877933,0" user="抖擞人生">掉两万以下了，再上两万</d>
<d p="114.49,1,24,7154951369349139237,1665895188590,0,1116726203782727,0" user="浩荡起航">点关注哦！别把娜娜弄丢了</d>
<gift ts="114.89" user="穿越时空" giftname="小心心" giftcount="1"></gift>
<d p="114.89,1,24,7154951369349139237,1665895188993,0,3531237609440990,0" user="琳晴钰">交朋友交朋友交朋友交朋友交朋友交朋友交朋友交朋友交朋友交朋友</d>
<gift ts="114.90" user="空姐走秀" giftname="小心心" giftcount="20"></gift>
<gift ts="115.30" user="何何" giftname="小心心" giftcount="1"></gift>
<gift ts="115.60" user="谭林" giftname="小心心" giftcount="4"></gift>
<d p="115.71,1,24,7154951369349139237,1665895189808,0,105712221343,0" user="**华哥：">点关注哦！别把娜娜弄丢了</d>
<gift ts="115.91" user="用户679598725741" giftname="小心心" giftcount="1"></gift>
<gift ts="116.42" user="无～情。。。" giftname="小心心" giftcount="1"></gift>
<gift ts="116.43" user="西西" giftname="入团卡" giftcount="1"></gift>
<d p="116.44,1,24,7154951369349139237,1665895190535,0,53383561684,0" user="穿越时空">点关注哦！别把娜娜弄丢了</d>
<gift ts="116.64" user="空姐走秀" giftname="小心心" giftcount="21"></gift>
<gift ts="117.27" user="无～情。。。" giftname="小心心" giftcount="4"></gift>
<d p="117.28,1,24,7154951369349139237,1665895191375,0,104637413089,0" user="玲姐">点关注哦！别把娜娜弄丢了</d>
<gift ts="118.05" user="空姐走秀" giftname="小心心" giftcount="22"></gift>
<d p="118.06,1,24,7154951369349139237,1665895192162,0,98132628119,0" user="琼欣慧至">点关注哦！别把娜娜弄丢了</d>
<gift ts="118.25" user="用户679598725741" giftname="小心心" giftcount="1"></gift>
<d p="118.68,1,24,7154951369349139237,1665895192778,0,102934649207,0" user="阿唐">娜娜咩在偷懒</d>
<gift ts="119.06" user="为你而来" giftname="" giftcount="1"></gift>
<gift ts="119.07" user="何何" giftname="小心心" giftcount="1"></gift>
<d p="119.08,1,24,7154951369349139237,1665895193177,0,1380578081904591,0" user="光头大叔">点关注哦！别把娜娜弄丢了</d>
<gift ts="119.08" user="IamGzq得心应手" giftname="小心心" giftcount="1"></gift>
<gift ts="119.09" user="静霞琳呈" giftname="" giftcount="1"></gift>
<gift ts="119.47" user="阿东哥" giftname="小心心" giftcount="1"></gift>
<gift ts="119.47" user="西西" giftname="入团卡" giftcount="1"></gift>
<d p="119.48,1,24,7154951369349139237,1665895193573,0,106748859607,0" user="莲花芬芳">点关注哦！别把娜娜弄丢了</d>
<gift ts="119.48" user="空姐走秀" giftname="小心心" giftcount="23"></gift>
<d p="119.67,1,24,7154951369349139237,1665895193764,0,96966916250,0" user="用户1708229597470">娜就艺起喜欢</d>
<gift ts="120.26" user="无～情。。。" giftname="小心心" giftcount="5"></gift>
<d p="120.48,1,24,7154951369349139237,1665895194582,0,71910199933,0" user="yang杨">志成榜八点点关注</d>
<d p="120.49,1,24,7154951369349139237,1665895194589,0,106915901970,0" user="没有如果">娜姐带人很会</d>
<d p="120.68,1,24,7154951369349139237,1665895194780,0,99492950030,0" user="安娜">娜娜姐</d>
<gift ts="120.88" user="空姐走秀" giftname="小心心" giftcount="24"></gift>
<d p="120.89,1,24,7154951369349139237,1665895194989,0,80778542111,0" user="HPB">关注榜三的艺艺</d>
<d p="120.90,1,24,7154951369349139237,1665895194994,0,93016741652,0" user="西西">点关注哦！别把娜娜弄丢了</d>
<d p="121.27,1,24,7154951369349139237,1665895195372,0,95739864498,0" user="昌华冻品（关注必回）">交朋友交朋友交朋友交朋友交朋友交朋友交朋友交朋友交朋友交朋友交朋友交朋友交朋友交朋友交朋友交朋友交朋</d>
<gift ts="121.47" user="都挺好" giftname="" giftcount="1"></gift>
<d p="121.48,1,24,7154951369349139237,1665895195577,0,3531237609440990,0" user="琳晴钰">交朋友交朋友交朋友交朋友交朋友交朋友交朋友交朋友交朋友交朋友</d>
<gift ts="121.67" user="用户6933630906188" giftname="小心心" giftcount="1"></gift>
<d p="121.68,1,24,7154951369349139237,1665895195782,0,1591715329223032,0" user="～单纯～">换换新歌</d>
<gift ts="122.06" user="IamGzq得心应手" giftname="小心心" giftcount="1"></gift>
<gift ts="122.07" user="阿东哥" giftname="小心心" giftcount="1"></gift>
<d p="122.27,1,24,7154951369349139237,1665895196363,0,109106148805,0" user="我本善良">点关注哦！别把娜娜弄丢了</d>
<gift ts="122.27" user="何何" giftname="小心心" giftcount="1"></gift>
<d p="122.47,1,24,7154951369349139237,1665895196564,0,3945469598512792,0" user="老谢来了">好听</d>
<gift ts="123.12" user="空姐走秀" giftname="小心心" giftcount="25"></gift>
<d p="123.13,1,24,7154951369349139237,1665895197225,0,62244249972,0" user="枝江代驾小哥哥">代驾小哥哥来了。</d>
<gift ts="123.30" user="无～情。。。" giftname="小心心" giftcount="5"></gift>
<gift ts="123.70" user="黑妺" giftname="" giftcount="1"></gift>
<d p="123.71,1,24,7154951369349139237,1665895197812,0,2744831192077086,0" user="六安好物分享">关注关注关注关注关注关注关注关注关注[玫瑰][玫瑰][玫瑰][玫瑰][玫瑰][玫瑰][玫瑰][玫瑰][玫瑰][玫瑰][玫瑰][玫瑰][比心][比心][比心][比心][比心][比心][比心][比心][比心][比心][比心][比心][比心][比心]</d>
<gift ts="124.11" user="空姐走秀" giftname="小心心" giftcount="26"></gift>
<d p="124.11,1,24,7154951369349139237,1665895198213,0,79773143985,0" user="上善若(水)">点关注哦！别把娜娜弄丢了</d>
<d p="124.32,1,24,7154951369349139237,1665895198413,0,70767539376,0" user="我就喜欢你">都好优秀</d>
<gift ts="124.52" user="用户6933630906188" giftname="小心心" giftcount="1"></gift>
<d p="124.53,1,24,7154951369349139237,1665895198628,0,109628662819,0" user="蓝鯨">志成优秀</d>
<d p="125.31,1,24,7154951369349139237,1665895199408,0,104747797573,0" user="永远的回忆">点关注哦！别把娜娜弄丢了</d>
<d p="125.32,1,24,7154951369349139237,1665895199416,0,102934649207,0" user="阿唐">娜娜咩在偷懒</d>
<gift ts="125.92" user="空姐走秀" giftname="小心心" giftcount="27"></gift>
<gift ts="126.33" user="都挺好" giftname="小心心" giftcount="1"></gift>
<d p="126.34,1,24,7154951369349139237,1665895200437,0,1785240049441294,0" user="我是天上人">[比心][比心][比心][比心][比心][比心][赞]</d>
<d p="126.74,1,24,7154951369349139237,1665895200842,0,1925940019992232,0" user="为你而来">点关注哦！别把娜娜弄丢了</d>
<d p="126.75,1,24,7154951369349139237,1665895200847,0,103188668795,0" user="樊凡">都棒棒哒[赞][赞][赞]</d>
<gift ts="126.95" user="空姐走秀" giftname="小心心" giftcount="28"></gift>
<d p="127.13,1,24,7154951369349139237,1665895201226,0,3531237609440990,0" user="琳晴钰">交朋友交朋友交朋友交朋友交朋友交朋友交朋友交朋友交朋友交朋友</d>
<gift ts="127.13" user="何何" giftname="小心心" giftcount="1"></gift>
<d p="127.33,1,24,7154951369349139237,1665895201428,0,68634942450,0" user="毛豆">昊艺嗓子不好，跳舞就行帅</d>
<d p="127.34,1,24,7154951369349139237,1665895201436,0,99560292341,0" user="江福慧">点关注哦！别把娜娜弄丢了</d>
<d p="127.74,1,24,7154951369349139237,1665895201840,0,96218132770,0" user="明天">志成在放松点就好了</d>
<gift ts="127.75" user="自强不息123" giftname="玫瑰" giftcount="1"></gift>
<gift ts="127.93" user="空姐走秀" giftname="小心心" giftcount="29"></gift>
<d p="128.13,1,24,7154951369349139237,1665895202224,0,108327517699,0" user="静霞琳呈">点关注哦！别把娜娜弄丢了</d>
<d p="128.94,1,24,7154951369349139237,1665895203039,0,80397645392,0" user="靓仔">娜娜你要记得给榜一眼'中人点关注人</d>
<d p="129.47,1,24,7154951369349139237,1665895203570,0,4393256281192900,0" user="家庭教育～译平">志成唱歌好听</d>
<d p="129.48,1,24,7154951369349139237,1665895203579,0,70767539376,0" user="我就喜欢你">都好优秀</d>
<gift ts="129.50" user="空姐走秀" giftname="小心心" giftcount="30"></gift>
<gift ts="129.51" user="都挺好" giftname="小心心" giftcount="1"></gift>
<gift ts="129.56" user="何何" giftname="小心心" giftcount="1"></gift>
<d p="130.07,1,24,7154951369349139237,1665895204173,0,93042110071,0" user="小">小牛嗨</d>
<d p="130.09,1,24,7154951369349139237,1665895204184,0,104456050950,0" user="惠姐">今天状态好</d>
<gift ts="130.89" user="自强不息123" giftname="玫瑰" giftcount="1"></gift>
<d p="131.10,1,24,7154951369349139237,1665895205198,0,74632092289,0" user="小女王">小牛优秀</d>
<d p="131.11,1,24,7154951369349139237,1665895205208,0,4340471743389443,0" user="妹儿">志诚棒</d>
<gift ts="131.68" user="空姐走秀" giftname="小心心" giftcount="30"></gift>
<d p="132.49,1,24,7154951369349139237,1665895206587,0,3531237609440990,0" user="琳晴钰">交朋友交朋友交朋友交朋友交朋友交朋友交朋友交朋友交朋友交朋友</d>
<d p="132.89,1,24,7154951369349139237,1665895206992,0,96061122021,0" user="最后的风度">[鼓掌][鼓掌][鼓掌][鼓掌]</d>
<gift ts="132.90" user="芳芳爱看剧" giftname="" giftcount="1"></gift>
<d p="133.70,1,24,7154951369349139237,1665895207802,0,57718649149,0" user="珝彤">志成[赞][赞][赞][赞][赞]</d>
<d p="134.93,1,24,7154951369349139237,1665895209026,0,79551200555,0" user="伪汉子">喜欢娜娜[比心][比心][比心]</d>
<d p="135.32,1,24,7154951369349139237,1665895209414,0,2853953637202775,0" user="峰回路转">[一起加油][一起加油][一起加油][一起加油][一起加油][一起加油]</d>
<gift ts="135.57" user="大青子" giftname="" giftcount="1"></gift>
<d p="136.30,1,24,7154951369349139237,1665895210401,0,1975148180668907,0" user="巍巍岁月">娜娜搞艺术有才华，比昊瀚还厉害！</d>
<d p="136.31,1,24,7154951369349139237,1665895210413,0,99010349140,0" user="一生有你">上3万</d>
